opentaxforms/Form.py
opentaxforms/__init__.py
opentaxforms/cmds.py
opentaxforms/config.py
opentaxforms/db.py
opentaxforms/extractFillableFields.py
opentaxforms/html.py
opentaxforms/irs.py
opentaxforms/link.py
opentaxforms/main.py
opentaxforms/refs.py
opentaxforms/schema.py
opentaxforms/serve.py
opentaxforms/ut.py
opentaxforms/version.py
opentaxforms/xmp.py
opentaxforms/static/allpdfnames.txt
opentaxforms/static/css/styles.css
opentaxforms/static/img/arrow_next_32px.png
opentaxforms/static/img/arrow_next_gray_32px.png
opentaxforms/static/img/arrow_prev_32px.png
opentaxforms/static/img/arrow_prev_gray_32px.png
opentaxforms/static/js/basil.js
opentaxforms/static/js/knockout-3.4.0.js
opentaxforms/static/js/opentaxforms.js
opentaxforms/template/form.html
opentaxforms-0.4.19.data/scripts/otf
opentaxforms-0.4.19.dist-info/top_level.txt
opentaxforms-0.4.19.dist-info/METADATA
opentaxforms-0.4.19.dist-info/DESCRIPTION.rst
opentaxforms-0.4.19.dist-info/metadata.json
opentaxforms-0.4.19.dist-info/WHEEL
opentaxforms-0.4.19.dist-info/RECORD
