Metadata-Version: 2.0
Name: opentaxforms
Version: 0.4.19
Summary: Modernizes tax forms and provides an API for new tax form interfaces
Home-page: http://github.com/jsaponara/opentaxforms/
Author: John Saponara
Author-email: john@opentaxforms.org
License: Affero GNU General Public License v3
Platform: any
Classifier: Programming Language :: Python
Classifier: Development Status :: 3 - Alpha
Classifier: Natural Language :: English
Classifier: Environment :: Web Environment
Classifier: Intended Audience :: Developers
Classifier: License :: OSI Approved :: GNU Affero General Public License v3 or later (AGPLv3+)
Classifier: Operating System :: OS Independent
Classifier: Topic :: Office/Business :: Financial
Classifier: Topic :: Internet :: WWW/HTTP :: Dynamic Content
Requires-Dist: Pint (>=0.7.2)
Requires-Dist: argparse (>=1.2.1)
Requires-Dist: lxml (>=3.6.4)
Requires-Dist: SQLAlchemy (>=1.0.15)
Requires-Dist: pdfminer (>=20140328)
Requires-Dist: Flask (==0.11.1)
Requires-Dist: Flask-Restless (==0.17.0)
Requires-Dist: Flask-SQLAlchemy (==2.1)
